{
  "id": "LOV-1955-06-30-26",
  "type": "statute",
  "title": "Lov om utførselsavgift på fisk og fiskevarer.",
  "short_name": "Lov om utførselsavgift på fiskevarer",
  "status": "in_force",
  "issued_date": "1955-06-30",
  "in_force_date": "1955-06-30",
  "url": "https://lovdata.no/dokument/NLO/lov/1955-06-30-26",
  "description": "Ingestion mode: full_text. Full-text ingestion is explicitly permitted by current policy. Attribution: Lovdata (official source) with source link and NLOD 2.0 attribution for covered content. Policy: full-text statute ingestion permitted for this source scope.",
  "provisions": [
    {
      "provision_ref": "1",
      "section": "1",
      "content": "Ved utførsel av saltvannsfisk, herunder laks, og andre sjødyr og produkter herav skal det betales en avgift som fastsettes av Kongen. Som utførsel regnes også re-eksport og direkte levering til utlandet fra norsk fiske- eller fangstfartøy.\nUnntatt fra avgiften er sjøørret samt produkter av hval fanget på den sydlige halvkule.\nAvgiften oppkreves av Tollvesenet og er grunnlag for utlegg.​2\n1 Endret ved lover 9 des 1955 nr. 12, 14 juni 1963 nr. 10, 26 juni 1992 nr. 86 (i kraft 1 jan 1993 iflg. res. 23 okt 1992 nr. 765).\n2 Jfr. tvangsfullbl. kap. 7.",
      "metadata": {
        "source": "lovdata",
        "source_node_id": "PARAGRAF_1",
        "source_heading": "§ 1."
      }
    },
    {
      "provision_ref": "2",
      "section": "2",
      "content": "Avgiften skal etter Kongens nærmere bestemmelse​2 nyttes til sosiale tiltak til fordel for fiskere – så som sikring av en garantiordning for lottfiskere, til tilskott til folketrygdavgiften for fiskere og fangstmenn og til tilskott til pensjonstrygden for fiskere.\n1 Endret ved lover 9 des 1955 nr. 12, 2 mars 1956 nr. 5, 28 juni 1957 nr. 13, 12 des 1958 nr. 22, 14 juni 1963 nr. 10, 29 jan 1971 nr. 20.\n2 Jfr. forskrift 19 mai 1972 nr. 2.",
      "metadata": {
        "source": "lovdata",
        "source_node_id": "PARAGRAF_2",
        "source_heading": "§ 2."
      }
    },
    {
      "provision_ref": "3",
      "section": "3",
      "content": "Kongen kan gi nærmere forskrifter til gjennomføring av denne lov, således om utregning, oppkreving og betaling av avgiften.​2\n1 Endret ved lov 9 des 1955 nr. 12.\n2 Jfr. forskrifter 30 sep 1977 nr. 1, 28 aug 1987 nr. 704.",
      "metadata": {
        "source": "lovdata",
        "source_node_id": "PARAGRAF_3",
        "source_heading": "§ 3."
      }
    },
    {
      "provision_ref": "4",
      "section": "4",
      "content": "Denne lov trer i kraft fra den tid Kongen bestemmer.​1\n1 Fra 1 jan 1956 iflg. res. 22 des 1955.",
      "metadata": {
        "source": "lovdata",
        "source_node_id": "PARAGRAF_4",
        "source_heading": "§ 4."
      }
    },
    {
      "provision_ref": "5",
      "section": "5",
      "content": "Fra den dag loven trer i kraft oppheves følgende lovbestemmelser: – – -.",
      "metadata": {
        "source": "lovdata",
        "source_node_id": "PARAGRAF_5",
        "source_heading": "§ 5."
      }
    }
  ],
  "provision_versions": [
    {
      "provision_ref": "1",
      "section": "1",
      "content": "Ved utførsel av saltvannsfisk, herunder laks, og andre sjødyr og produkter herav skal det betales en avgift som fastsettes av Kongen. Som utførsel regnes også re-eksport og direkte levering til utlandet fra norsk fiske- eller fangstfartøy.\nUnntatt fra avgiften er sjøørret samt produkter av hval fanget på den sydlige halvkule.\nAvgiften oppkreves av Tollvesenet og er grunnlag for utlegg.​2\n1 Endret ved lover 9 des 1955 nr. 12, 14 juni 1963 nr. 10, 26 juni 1992 nr. 86 (i kraft 1 jan 1993 iflg. res. 23 okt 1992 nr. 765).\n2 Jfr. tvangsfullbl. kap. 7.",
      "metadata": {
        "source": "lovdata",
        "source_node_id": "PARAGRAF_1",
        "source_heading": "§ 1."
      }
    },
    {
      "provision_ref": "2",
      "section": "2",
      "content": "Avgiften skal etter Kongens nærmere bestemmelse​2 nyttes til sosiale tiltak til fordel for fiskere – så som sikring av en garantiordning for lottfiskere, til tilskott til folketrygdavgiften for fiskere og fangstmenn og til tilskott til pensjonstrygden for fiskere.\n1 Endret ved lover 9 des 1955 nr. 12, 2 mars 1956 nr. 5, 28 juni 1957 nr. 13, 12 des 1958 nr. 22, 14 juni 1963 nr. 10, 29 jan 1971 nr. 20.\n2 Jfr. forskrift 19 mai 1972 nr. 2.",
      "metadata": {
        "source": "lovdata",
        "source_node_id": "PARAGRAF_2",
        "source_heading": "§ 2."
      }
    },
    {
      "provision_ref": "3",
      "section": "3",
      "content": "Kongen kan gi nærmere forskrifter til gjennomføring av denne lov, således om utregning, oppkreving og betaling av avgiften.​2\n1 Endret ved lov 9 des 1955 nr. 12.\n2 Jfr. forskrifter 30 sep 1977 nr. 1, 28 aug 1987 nr. 704.",
      "metadata": {
        "source": "lovdata",
        "source_node_id": "PARAGRAF_3",
        "source_heading": "§ 3."
      }
    },
    {
      "provision_ref": "4",
      "section": "4",
      "content": "Denne lov trer i kraft fra den tid Kongen bestemmer.​1\n1 Fra 1 jan 1956 iflg. res. 22 des 1955.",
      "metadata": {
        "source": "lovdata",
        "source_node_id": "PARAGRAF_4",
        "source_heading": "§ 4."
      }
    },
    {
      "provision_ref": "5",
      "section": "5",
      "content": "Fra den dag loven trer i kraft oppheves følgende lovbestemmelser: – – -.",
      "metadata": {
        "source": "lovdata",
        "source_node_id": "PARAGRAF_5",
        "source_heading": "§ 5."
      }
    }
  ]
}